bmb/schema/__init__.py
bmb/schema/invoice_document.py
bmb/schema/metadata.py
bmb/schema/standard.py
bmb/schema/util.py
bmb/schema/version.py
bmb/schema/invoice/pdf.py
bmb/schema/invoice/xml_serializer.py
bmb/schema/resources/documents_report_v0.xsd
bmb/schema/resources/insertion_report_v0.xml
bmb/schema/resources/insertion_report_v0.xsd
bmb/schema/resources/invoice.css
bmb/schema/resources/invoice2.css
bmb/schema/resources/sender_whitelist_change_request_v0.xsd
bmb/schema/resources/sender_whitelist_change_requests_v0.xsd
bmb/schema/resources/sender_whitelist_decision_v0.xsd
bmb/schema/resources/sender_whitelist_peers_v0.xsd
bmb/schema/resources/sender_whitelist_whitelist_v0.xsd
bmb/schema/resources/standard_invoice.xml
bmb/schema/resources/standard_invoice.xsd
bmb/schema/resources/standard_invoice_v1.xml
bmb/schema/resources/standard_invoice_v1.xsd
bmb/schema/resources/standard_invoice_v2.xml
bmb/schema/resources/standard_invoice_v2.xsd
bmb/schema/resources/standard_invoice_v3.xsd
bmb/schema/resources/standard_invoice_v3_good.xml
bmb/schema/resources/standard_invoice_v4.xsd
bmb/schema/resources/standard_invoice_v4_good.xml
bmb/schema/resources/standard_invoice_v4_jinja2.xml
bmb/schema/resources/standard_invoice_v5.j2.html
bmb/schema/resources/standard_invoice_v5.j2.xml
bmb/schema/resources/standard_invoice_v5.xsd
bmb/schema/resources/standard_invoice_v5_2.j2.html
bmb/schema/resources/standard_invoice_v5_enriched_good.xml
bmb/schema/resources/standard_invoice_v5_good.xml
bmb/schema/resources/standard_invoices.xml
bmb/schema/resources/standard_invoices_v1.xml
bmb/schema/resources/standard_invoices_v2.xml
bmb_schema-0.3.3.dist-info/METADATA
bmb_schema-0.3.3.dist-info/WHEEL
bmb_schema-0.3.3.dist-info/top_level.txt
bmb_schema-0.3.3.dist-info/RECORD
